Metadata-Version: 2.1
Name: shzLibs
Version: 0.0.1
Summary: Personal support tools in the development of varied projects
Author: Eliseu Brito
Author-email: eliseubrito776@gmail.com
License: MIT License
Keywords: shz tools shzlibs
License-File: LICENSE
